<xml xmlns="https://developers.google.com/blockly/xml"><block type="component_event" id="y9tqg*weexV6}=FVH)5}" x="-63" y="-962"><mutation xmlns="http://www.w3.org/1999/xhtml" component_name="Profile screen" component_type="Screen" parent_id="undefined" event_id="Opens" was_updated="true"/><field name="component_id">a4aa2253-f4ed-43e1-9218-be617dbafa58</field><field name="event_id">Opens</field><statement name="input_do"><block type="controls_if" id="N{rih,(`fjHT|r9(Zu0:"><mutation else="1"/><value name="IF0"><block type="logic_compare" id="X-Mrv~:9D{fx4G5m*@*}"><field name="OP">EQ</field><value name="A"><block type="variables_get_dynamic" id="vW)Q[u49@J:(8F#n+.u("><field name="SCOPE">CLOUD</field><value name="NAME"><shadow type="text" id="J%C]u9gs/yfHh7w`7*-="><field name="TEXT">name</field></shadow><block type="text_join" id="a^_K^mVnX7bVCea;h7w/"><mutation items="2"/><value name="ADD0"><block type="text" id="T_D-rdzJG}jZk)JP[7s1"><field name="TEXT">users/</field></block></value><value name="ADD1"><block type="variables_get" id="4v_HztuG6n)[|EP8HZ(v"><mutation xmlns="http://www.w3.org/1999/xhtml" saved_name="app variable userID"/><field name="VAR">95aaa81c-290e-4fd0-82c0-2a41e24a2ea9</field></block></value></block></value></block></value><value name="B"><block type="logic_null" id="s)_h3%j*E.b6MYMg~m{B"/></value></block></value><statement name="DO0"><block type="variables_set_dynamic" id="{_ongn(e=l2G]G6d#=Xa"><field name="SCOPE">CLOUD</field><value name="NAME"><shadow type="text" id="d1!h~p:,%=KvwbT%#D9D"><field name="TEXT">name</field></shadow><block type="text_join" id="kU|*KBO~!([;{TW|hxxP"><mutation items="2"/><value name="ADD0"><block type="text" id="t2))vZ_t?;d[A}XV7rF,"><field name="TEXT">users/</field></block></value><value name="ADD1"><block type="variables_get" id="t|[.5*)CAozrY]/py;L6"><mutation xmlns="http://www.w3.org/1999/xhtml" saved_name="app variable userID"/><field name="VAR">95aaa81c-290e-4fd0-82c0-2a41e24a2ea9</field></block></value></block></value><value name="VALUE"><block type="object_create" id="rg3hX@njU*t~g!%1S~Tz"><mutation xmlns="http://www.w3.org/1999/xhtml" num_fields="2"><field name="name"/><field name="entries"/></mutation><field name="field1">name</field><field name="field2">entries</field><value name="field_input1"><block type="logic_null" id="0h.G=K%dAAcMJ2hekt%o"/></value><value name="field_input2"><block type="object_create" id="0$nfIy}p,_doMmENr[5f"><mutation xmlns="http://www.w3.org/1999/xhtml" num_fields="1"><field name="placeholder"/></mutation><field name="field1">placeholder</field><value name="field_input1"><block type="text" id="Q!r~8{CG^)^q6.{}/|qs"><field name="TEXT">temp</field></block></value></block></value></block></value></block></statement><statement name="ELSE"><block type="setter" id="MbBje(A9^G3F*@YKb{jy"><mutation xmlns="http://www.w3.org/1999/xhtml" component_name="Name Label" parent_id="undefined"/><field name="component_id">8cc96134-c353-4c06-ba37-fdd8fcb7a8ef</field><field name="field_name">Text</field><value name="field_value"><shadow type="text" id="4i@Iz0Y;nj!;-qjQSAfK"><field name="TEXT">Label</field></shadow><block type="text_join" id="._ZOE(I7j^29P99lM,^_"><mutation items="3"/><value name="ADD0"><block type="text" id="{bTJUJK8xAP2y.M}B5d="><field name="TEXT">Welcome </field></block></value><value name="ADD1"><block type="variables_get_dynamic" id="NQ8(j7qT]z-*S@CI1V^."><field name="SCOPE">CLOUD</field><value name="NAME"><shadow type="text" id=";cib6{cB[+U:QJW=8]p)"><field name="TEXT">name</field></shadow><block type="text_join" id="o2Eu-*GBdzr*-T?1_4A4"><mutation items="3"/><value name="ADD0"><block type="text" id="jhG!8qV@Z+?9z1m(L{|y"><field name="TEXT">users/</field></block></value><value name="ADD1"><block type="variables_get" id="3V0{PVvGdNiLZyv8H?e_"><mutation xmlns="http://www.w3.org/1999/xhtml" saved_name="app variable userID"/><field name="VAR">95aaa81c-290e-4fd0-82c0-2a41e24a2ea9</field></block></value><value name="ADD2"><block type="text" id="2ZiS0%v!;L_;)@0aN.4t"><field name="TEXT">/name</field></block></value></block></value></block></value><value name="ADD2"><block type="text" id="0Inn67rUA(5gx%5N-sjz"><field name="TEXT">!</field></block></value></block></value></block></statement><next><block type="controls_if" id="F+9N_?4Uo66+(x2y(pmU"><value name="IF0"><block type="logic_compare" id="=}NcFLJi@gSZ_^[HxYLi"><field name="OP">NEQ</field><value name="A"><block type="variables_get_dynamic" id="v]ib-)Ll(LLc{m)e7EQf"><field name="SCOPE">CLOUD</field><value name="NAME"><shadow type="text" id="J%C]u9gs/yfHh7w`7*-="><field name="TEXT">name</field></shadow><block type="text_join" id="j+`P4Ju1LA*iuWVw%=MO"><mutation items="4"/><value name="ADD0"><block type="text" id="clc5a!46]bkeY;AJVN4m"><field name="TEXT">users/</field></block></value><value name="ADD1"><block type="variables_get" id="gA/IKgEzVTON$9ByX1CX"><mutation xmlns="http://www.w3.org/1999/xhtml" saved_name="app variable userID"/><field name="VAR">95aaa81c-290e-4fd0-82c0-2a41e24a2ea9</field></block></value><value name="ADD2"><block type="text" id="_:}iEW(a,d_WHO9Qht{N"><field name="TEXT">/entries/</field></block></value><value name="ADD3"><block type="text_join" id="}8=*IrZacJ_!9V`k,R]V" collapsed="true"><mutation items="5"/><value name="ADD0"><block type="device_current_date" id=")k6Y(kDnkk9/m]F}F^k-"><field name="TIME_PERIOD">MONTH</field></block></value><value name="ADD1"><block type="text" id="Jn!ieGScL/A_@,Gwtb^%"><field name="TEXT">-</field></block></value><value name="ADD2"><block type="device_current_date" id="(2$L+]~93Je0vC:1fMc`"><field name="TIME_PERIOD">DAY_OF_MONTH</field></block></value><value name="ADD3"><block type="text" id="Z%mgRC#w=u!.mkb1W,*9"><field name="TEXT">-</field></block></value><value name="ADD4"><block type="device_current_date" id=":ovlixyCU~cB`_]f=:g}"><field name="TIME_PERIOD">YEAR</field></block></value></block></value></block></value></block></value><value name="B"><block type="logic_null" id="b:R}@g+x.V[{kZO8$C_Z"/></value></block></value><statement name="DO0"><block type="setter" id="HgA)Cr*a,vT21l5:#DF7"><mutation xmlns="http://www.w3.org/1999/xhtml" component_name="Stat_Label" parent_id="undefined"/><field name="component_id">7e4f25a4-a0ec-4420-90b8-ae9861ff730f</field><field name="field_name">Text</field><value name="field_value"><shadow type="text" id="-Pe:1ZW[m[!`trN#8eJ_"><field name="TEXT">Label</field></shadow><block type="text_join" id="@Z-Gr?m7Jv4ym8;z3:kp"><mutation items="11"/><value name="ADD0"><block type="text" id="TYjP9F*#6h@f,5.:6K=)"><field name="TEXT">Your stats for today were:</field></block></value><value name="ADD1"><block type="newline" id="bF;P}7A89%6Ow*+2GlmL"/></value><value name="ADD2"><block type="text" id="%eYimkgbgjZ#V^j9O=$U"><field name="TEXT">WPM: </field></block></value><value name="ADD3"><block type="math_round" id="C%]ORxk=o43oyqOS`fZ2"><field name="OP">ROUND</field><value name="NUM"><shadow type="math_number" id="%chUP8v2j.C4x=/:D!;$"><field name="NUM">3.1</field></shadow><block type="variables_get_dynamic" id="6!]10_T~J]xi:Y*~S1p*"><field name="SCOPE">CLOUD</field><value name="NAME"><shadow type="text" id="J%C]u9gs/yfHh7w`7*-="><field name="TEXT">name</field></shadow><block type="text_join" id="e,hc/44i7aW406VxV*m%"><mutation items="5"/><value name="ADD0"><block type="text" id="_ZQdNDGaDR1X+y1FhdDS"><field name="TEXT">users/</field></block></value><value name="ADD1"><block type="variables_get" id="llewHkkPXg)5/bg`,|P/"><mutation xmlns="http://www.w3.org/1999/xhtml" saved_name="app variable userID"/><field name="VAR">95aaa81c-290e-4fd0-82c0-2a41e24a2ea9</field></block></value><value name="ADD2"><block type="text" id="*,nzzUDfu_#cfyr[i]/8"><field name="TEXT">/entries/</field></block></value><value name="ADD3"><block type="text_join" id="Q-lpI-s#T-:8.^l-0hMM" collapsed="true"><mutation items="5"/><value name="ADD0"><block type="device_current_date" id="w_?xUrO3$XO{~EMR*gv?"><field name="TIME_PERIOD">MONTH</field></block></value><value name="ADD1"><block type="text" id="]UF%C|X0+eoRCZ,8d^FD"><field name="TEXT">-</field></block></value><value name="ADD2"><block type="device_current_date" id="SxE8?wA+VTZZqlPr=cM:"><field name="TIME_PERIOD">DAY_OF_MONTH</field></block></value><value name="ADD3"><block type="text" id="WPfAM@E^6`iW-nYUHH*S"><field name="TEXT">-</field></block></value><value name="ADD4"><block type="device_current_date" id="hpSl9,pD::JHJ@;v;~+~"><field name="TIME_PERIOD">YEAR</field></block></value></block></value><value name="ADD4"><block type="text" id="4yCHs%[}a^Wbu-=^jD-C"><field name="TEXT">/wpm</field></block></value></block></value></block></value></block></value><value name="ADD4"><block type="newline" id=",:J;OL5~:2sw{UC=TJOu"/></value><value name="ADD5"><block type="text" id="ie-BlkZOWaD4!Mp+E{@S"><field name="TEXT">Accuracy: </field></block></value><value name="ADD6"><block type="math_decimal_places" id="WY2sp#(WAyw~7]ZYww_w"><value name="INPUT_NUM"><shadow type="math_number" id="ZK~ij4!ss7qUS7ezGu=T"><field name="NUM">3.1415</field></shadow><block type="variables_get_dynamic" id="4?$P$nLU==6e)u^2NY3."><field name="SCOPE">CLOUD</field><value name="NAME"><shadow type="text" id="J%C]u9gs/yfHh7w`7*-="><field name="TEXT">name</field></shadow><block type="text_join" id=":wJW|~p%Fws+:pLZyV68"><mutation items="5"/><value name="ADD0"><block type="text" id="I9)q_Uj0@D7@;!f,sWC8"><field name="TEXT">users/</field></block></value><value name="ADD1"><block type="variables_get" id="x8Lm;tO=bBvi40!/65v%"><mutation xmlns="http://www.w3.org/1999/xhtml" saved_name="app variable userID"/><field name="VAR">95aaa81c-290e-4fd0-82c0-2a41e24a2ea9</field></block></value><value name="ADD2"><block type="text" id="`/n7vigmbc7ouExY.^/)"><field name="TEXT">/entries/</field></block></value><value name="ADD3"><block type="text_join" id="!5:^$`~VBD3e6KF~H8~Y" collapsed="true"><mutation items="5"/><value name="ADD0"><block type="device_current_date" id="3[2c0eg;Wrcn4sox!s5U"><field name="TIME_PERIOD">MONTH</field></block></value><value name="ADD1"><block type="text" id="F5FUT5_Y]y*,Dcza*^[y"><field name="TEXT">-</field></block></value><value name="ADD2"><block type="device_current_date" id="bQr1[s[Qf!_%XsJc^^!{"><field name="TIME_PERIOD">DAY_OF_MONTH</field></block></value><value name="ADD3"><block type="text" id="=P()D.ZUUp)U*j*EqmYP"><field name="TEXT">-</field></block></value><value name="ADD4"><block type="device_current_date" id="*#?G}^x|,`bwR,*f:1OE"><field name="TIME_PERIOD">YEAR</field></block></value></block></value><value name="ADD4"><block type="text" id="[RVv]K}~^nk=G*[0YC8+"><field name="TEXT">/accuracy</field></block></value></block></value></block></value><value name="DECIMAL_PLACES"><shadow type="math_number" id="Qyk{~L`K2QFF]0X+r4D_"><field name="NUM">1</field></shadow></value></block></value><value name="ADD7"><block type="text" id="F18jNl!VJ!/qYng2sv.E"><field name="TEXT">%</field></block></value><value name="ADD8"><block type="newline" id="hC`%-CyFvq$QTkjq]z1("/></value><value name="ADD9"><block type="text" id="LNzTU=:WPZg8Kv4^O0+p"><field name="TEXT">Score: </field></block></value><value name="ADD10"><block type="variables_get_dynamic" id="*$)UFjT*/4}D+sY3o%;k"><field name="SCOPE">CLOUD</field><value name="NAME"><shadow type="text" id="J%C]u9gs/yfHh7w`7*-="><field name="TEXT">name</field></shadow><block type="text_join" id="qi[x{^F^*A:I.FDI[@_R"><mutation items="5"/><value name="ADD0"><block type="text" id="Z|mk~8tD{Z,XF-ruiY,B"><field name="TEXT">users/</field></block></value><value name="ADD1"><block type="variables_get" id="3@mGelmQHmKCyM0J`Doe"><mutation xmlns="http://www.w3.org/1999/xhtml" saved_name="app variable userID"/><field name="VAR">95aaa81c-290e-4fd0-82c0-2a41e24a2ea9</field></block></value><value name="ADD2"><block type="text" id="SDTJ2a%lr:}Vc#$,xwis"><field name="TEXT">/entries/</field></block></value><value name="ADD3"><block type="text_join" id="DXnUGo`v]DSuuIqb?]58" collapsed="true"><mutation items="5"/><value name="ADD0"><block type="device_current_date" id="$6(UL`W^mea6+fQ!Hz4s"><field name="TIME_PERIOD">MONTH</field></block></value><value name="ADD1"><block type="text" id="kClxB^Muv3s^HBgQ#G5$"><field name="TEXT">-</field></block></value><value name="ADD2"><block type="device_current_date" id="g#Sua|^iYpw+:jIRgD61"><field name="TIME_PERIOD">DAY_OF_MONTH</field></block></value><value name="ADD3"><block type="text" id=":0kWz?BdSUj2)vgrL%p1"><field name="TEXT">-</field></block></value><value name="ADD4"><block type="device_current_date" id="ay{wQdK53Mnqv=F|+B!4"><field name="TIME_PERIOD">YEAR</field></block></value></block></value><value name="ADD4"><block type="text" id="`uhQCeve^rx9Gdl!Nn]Z"><field name="TEXT">/score</field></block></value></block></value></block></value></block></value></block></statement></block></next></block></statement></block><block type="component_event" id="A7jq.~853Ip1CijO69;G" x="959" y="-82"><mutation xmlns="http://www.w3.org/1999/xhtml" component_name="Sign Out Button" component_type="Button" parent_id="undefined" event_id="Click" was_updated="true"/><field name="component_id">b495cc07-e99d-4e1e-aa6f-fe283f80f1fe</field><field name="event_id">Click</field><statement name="input_do"><block type="signin_sign_out" id="[@v-x$^TCW64+}9{1hsF"><next><block type="variables_set" id="I52IRzOX!_?7ClIYhdxZ"><mutation xmlns="http://www.w3.org/1999/xhtml" saved_name="app variable userID"/><field name="VAR">95aaa81c-290e-4fd0-82c0-2a41e24a2ea9</field><value name="VALUE"><block type="logic_null" id="wDaTSz$(g8g;a(ka~fiJ"/></value><next><block type="controls_navigate_new" id="LZv8udB8a.g,vJ@96bq+"><value name="COMPONENT"><shadow type="any_component_component_dropdown" id="OD$qnKZ}-gR.{YjY``6^"><mutation xmlns="http://www.w3.org/1999/xhtml" component_id="Sign up sceen" component_types_to_include="[&quot;Screen&quot;]"/><field name="component_id">a521dbaf-55fa-4a1c-92ff-b290b2f5c653</field></shadow></value></block></next></block></next></block></statement></block><block type="component_event" id="eGSffO0R#yMQDds*:Ate" x="941" y="101"><mutation xmlns="http://www.w3.org/1999/xhtml" component_name="Play Button" component_type="Button" parent_id="undefined" event_id="Click" was_updated="true"/><field name="component_id">f63f71d8-dc9f-44fc-85b8-2a5994e86bca</field><field name="event_id">Click</field><statement name="input_do"><block type="controls_navigate_new" id="j+xgZ$N1Sko`O@aMvv3/"><value name="COMPONENT"><shadow type="any_component_component_dropdown" id="rjYgFBj4Jy0+s6GuR1vI"><mutation xmlns="http://www.w3.org/1999/xhtml" component_id="Game Screen" component_types_to_include="[&quot;Screen&quot;]"/><field name="component_id">98c84839-ddd0-4235-8a2a-e162b0c19259</field></shadow></value></block></statement></block><block type="component_event" id="Sz3MQRC95[(|mb{6B^0E" x="50" y="274"><mutation xmlns="http://www.w3.org/1999/xhtml" component_name="Name Label" component_type="Label" parent_id="undefined" event_id="Click" was_updated="true"/><field name="component_id">8cc96134-c353-4c06-ba37-fdd8fcb7a8ef</field><field name="event_id">Click</field><statement name="input_do"><block type="setter" id="LQxK0w;KM,%`Rj|s8Qwz"><mutation xmlns="http://www.w3.org/1999/xhtml" component_name="Name Group" parent_id="undefined"/><field name="component_id">cf9d1576-f62b-46ba-a684-736295facc4f</field><field name="field_name">Visible</field><value name="field_value"><shadow type="logic_boolean" id="I)pwW!=bXX/a0Wymrw|Z"><field name="BOOL">TRUE</field></shadow></value><next><block type="setter" id="a)xUUd|B|E.yGHIuU5H6"><mutation xmlns="http://www.w3.org/1999/xhtml" component_name="Name Label" parent_id="undefined"/><field name="component_id">8cc96134-c353-4c06-ba37-fdd8fcb7a8ef</field><field name="field_name">Visible</field><value name="field_value"><shadow type="logic_boolean" id="lhiSIhXZtf;.,okINtly"><field name="BOOL">FALSE</field></shadow></value></block></next></block></statement></block><block type="component_event" id="k.6rwOfV$~yj!gQ^#|jA" x="443" y="282"><mutation xmlns="http://www.w3.org/1999/xhtml" component_name="Cancel Name Button" component_type="Button" parent_id="undefined" event_id="Click" was_updated="true"/><field name="component_id">6e79d7d8-a898-4c66-bd49-f4b40808eec6</field><field name="event_id">Click</field><statement name="input_do"><block type="setter" id="dA~kEUCeKisO;fIhhnzP"><mutation xmlns="http://www.w3.org/1999/xhtml" component_name="Name Group" parent_id="undefined"/><field name="component_id">cf9d1576-f62b-46ba-a684-736295facc4f</field><field name="field_name">Visible</field><value name="field_value"><shadow type="logic_boolean" id="Lh(WpK1K3PV0Lw{LU,$~"><field name="BOOL">FALSE</field></shadow></value><next><block type="setter" id=")750!5Qi_!V=Cg#R2h0p"><mutation xmlns="http://www.w3.org/1999/xhtml" component_name="Name Label" parent_id="undefined"/><field name="component_id">8cc96134-c353-4c06-ba37-fdd8fcb7a8ef</field><field name="field_name">Visible</field><value name="field_value"><shadow type="logic_boolean" id="8J?J0Ep0[/)?AKRXhN2]"><field name="BOOL">TRUE</field></shadow></value></block></next></block></statement></block><block type="component_event" id=",JA]GCnjESuf)Oi8dk|:" x="48" y="403"><mutation xmlns="http://www.w3.org/1999/xhtml" component_name="Save Name Button" component_type="Button" parent_id="undefined" event_id="Click" was_updated="true"/><field name="component_id">b2ca9fb2-11e6-4287-ae65-246e8fee6b95</field><field name="event_id">Click</field><statement name="input_do"><block type="controls_if" id="zC@!rueL}kKoeb7gP#Dd"><mutation else="1"/><value name="IF0"><block type="text_isEmpty" id="l7oW5M$6/N5P5:@U;{2D"><value name="VALUE"><shadow type="text" id="[L-Qd?T-LtiI7S7S|Nv+"><field name="TEXT"/></shadow><block type="set_get" id="C|S4|r3I*_].ReX_[8;["><mutation xmlns="http://www.w3.org/1999/xhtml" component_name="Name Input" parent_id="undefined"/><field name="component_id">90837499-7ceb-49c9-9411-b3bddb8c4bfc</field><field name="field_name">Text</field></block></value></block></value><statement name="DO0"><block type="setter" id="1V7KzB2N/kX~[Bpa.[ll"><mutation xmlns="http://www.w3.org/1999/xhtml" component_name="Name Input" parent_id="undefined"/><field name="component_id">90837499-7ceb-49c9-9411-b3bddb8c4bfc</field><field name="field_name">Hint</field><value name="field_value"><shadow type="text" id="6cDFNWHHG@u:$l`Az,gH"><field name="TEXT">Name cannot be empty</field></shadow></value></block></statement><statement name="ELSE"><block type="variables_set_dynamic" id="p`T`?MKIxpF-SwAV#T3Z"><field name="SCOPE">CLOUD</field><value name="NAME"><shadow type="text" id="=rG$:)T~3~Tfa!_la{w%"><field name="TEXT">name</field></shadow><block type="text_join" id="3!)~iou@9|Utrtee^VO4"><mutation items="3"/><value name="ADD0"><block type="text" id="g,6VZf=H*ar,5cWj4C*d"><field name="TEXT">users/</field></block></value><value name="ADD1"><block type="variables_get" id="{HwSToiXy2MC)./2IBwj"><mutation xmlns="http://www.w3.org/1999/xhtml" saved_name="app variable userID"/><field name="VAR">95aaa81c-290e-4fd0-82c0-2a41e24a2ea9</field></block></value><value name="ADD2"><block type="text" id="#0=ThQ*{]]*bLP#a1UWD"><field name="TEXT">/name</field></block></value></block></value><value name="VALUE"><block type="set_get" id=",F83#G2v/Cl3+/_p0NE."><mutation xmlns="http://www.w3.org/1999/xhtml" component_name="Name Input" parent_id="undefined"/><field name="component_id">90837499-7ceb-49c9-9411-b3bddb8c4bfc</field><field name="field_name">Text</field></block></value><next><block type="setter" id="xOewF`TI:Z:^W|$M.v,A"><mutation xmlns="http://www.w3.org/1999/xhtml" component_name="Name Label" parent_id="undefined"/><field name="component_id">8cc96134-c353-4c06-ba37-fdd8fcb7a8ef</field><field name="field_name">Text</field><value name="field_value"><shadow type="text" id="4i@Iz0Y;nj!;-qjQSAfK"><field name="TEXT">Label</field></shadow><block type="text_join" id="nXPm?qm[Pd;N_s;}jZtP"><mutation items="3"/><value name="ADD0"><block type="text" id="fBq2Dei)Wms5Yk-MBP`("><field name="TEXT">Welcome </field></block></value><value name="ADD1"><block type="variables_get_dynamic" id=",r.FFt+C79/=)/Y;BGLW"><field name="SCOPE">CLOUD</field><value name="NAME"><shadow type="text" id=";cib6{cB[+U:QJW=8]p)"><field name="TEXT">name</field></shadow><block type="text_join" id="#p*(qetoCBs9C;A]V=G8"><mutation items="3"/><value name="ADD0"><block type="text" id="zip{Z|HgHpByWr*jRD[0"><field name="TEXT">users/</field></block></value><value name="ADD1"><block type="variables_get" id="$,|9:,u@FU}N3]vuJ_js"><mutation xmlns="http://www.w3.org/1999/xhtml" saved_name="app variable userID"/><field name="VAR">95aaa81c-290e-4fd0-82c0-2a41e24a2ea9</field></block></value><value name="ADD2"><block type="text" id="Lkm{x5}8Xyp68=d`;pV)"><field name="TEXT">/name</field></block></value></block></value></block></value><value name="ADD2"><block type="text" id="2-oQ|I4lXl2pU|xt3jfo"><field name="TEXT">!</field></block></value></block></value><next><block type="setter" id="=yD$O;7m(52c9)]@(K(X"><mutation xmlns="http://www.w3.org/1999/xhtml" component_name="Name Group" parent_id="undefined"/><field name="component_id">cf9d1576-f62b-46ba-a684-736295facc4f</field><field name="field_name">Visible</field><value name="field_value"><shadow type="logic_boolean" id="KN[Qv.apdV0`gGs6ePa)"><field name="BOOL">FALSE</field></shadow></value><next><block type="setter" id="5{89,o|xPef$@{rFfb+8"><mutation xmlns="http://www.w3.org/1999/xhtml" component_name="Name Label" parent_id="undefined"/><field name="component_id">8cc96134-c353-4c06-ba37-fdd8fcb7a8ef</field><field name="field_name">Visible</field><value name="field_value"><shadow type="logic_boolean" id="Mt/!_B3Ne/8-HE_^$T]?"><field name="BOOL">TRUE</field></shadow></value></block></next></block></next></block></next></block></statement></block></statement></block></xml>